flake8_multiline_conditionals_comprehensions/__init__.py
flake8_multiline_conditionals_comprehensions/mcc_checker.py
flake8_multiline_conditionals_comprehensions-2.0.dist-info/LICENSE
flake8_multiline_conditionals_comprehensions-2.0.dist-info/METADATA
flake8_multiline_conditionals_comprehensions-2.0.dist-info/WHEEL
flake8_multiline_conditionals_comprehensions-2.0.dist-info/entry_points.txt
flake8_multiline_conditionals_comprehensions-2.0.dist-info/top_level.txt
flake8_multiline_conditionals_comprehensions-2.0.dist-info/RECORD
