Metadata-Version: 2.1
Name: flake8-multiline-conditionals-comprehensions
Version: 2.0
Summary: A flake8 plugin to make sure complex conditional expressions and comprehension expressions are split over several lines.
Home-page: https://github.com/atollk/flake8-multiline-conditionals-comprehensions
Author: Andreas Tollkötter
License: MIT
Keywords: flake8,comprehensions,conditional
Classifier: Framework :: Flake8
Classifier: Intended Audience :: Developers
Classifier: License :: OSI Approved :: MIT License
Classifier: Natural Language :: English
Classifier: Programming Language :: Python :: 3 :: Only
Classifier: Programming Language :: Python :: 3
Classifier: Programming Language :: Python :: 3.8
Classifier: Programming Language :: Python :: 3.9
Classifier: Programming Language :: Python :: 3.10
Classifier: Programming Language :: Python :: 3.11
Requires-Python: >=3.8
License-File: LICENSE
